labkey/__init__.py
labkey/api_wrapper.py
labkey/container.py
labkey/domain.py
labkey/exceptions.py
labkey/experiment.py
labkey/query.py
labkey/security.py
labkey/server_context.py
labkey/storage.py
labkey/utils.py
labkey-4.0.1.dist-info/licenses/LICENSE.txt
labkey-4.0.1.dist-info/METADATA
labkey-4.0.1.dist-info/WHEEL
labkey-4.0.1.dist-info/top_level.txt
labkey-4.0.1.dist-info/RECORD
